sushycli/__init__.py
sushycli/base.py
sushycli/base_chassis.py
sushycli/base_manager.py
sushycli/base_system.py
sushycli/base_vmedia.py
sushycli/chassis_inventory.py
sushycli/chassis_list.py
sushycli/manager_inventory.py
sushycli/manager_list.py
sushycli/manager_vmedia.py
sushycli/system_bios.py
sushycli/system_boot.py
sushycli/system_inventory.py
sushycli/system_list.py
sushycli/system_power.py
sushycli/utils.py
sushycli/version.py
sushycli/cmd/__init__.py
sushycli/cmd/sushycli.py
sushycli/tests/__init__.py
sushycli/tests/unit/__init__.py
sushycli/tests/unit/base.py
sushycli/tests/unit/test_base.py
sushycli/tests/unit/cmd/__init__.py
sushycli/tests/unit/cmd/test_sushycli.py
sushy_cli-0.4.0.dist-info/AUTHORS
sushy_cli-0.4.0.dist-info/LICENSE
sushy_cli-0.4.0.dist-info/METADATA
sushy_cli-0.4.0.dist-info/WHEEL
sushy_cli-0.4.0.dist-info/entry_points.txt
sushy_cli-0.4.0.dist-info/pbr.json
sushy_cli-0.4.0.dist-info/top_level.txt
sushy_cli-0.4.0.dist-info/RECORD
